[
  {
    "id": "ucsd-accessibility-review",
    "name": "ucsd-accessibility-review",
    "title": "UCSD Accessibility Review",
    "description": "Review UC San Diego web pages, documents, and app screens for common accessibility issues and WCAG-aligned remediation steps.",
    "category": "Compliance",
    "status": "in-progress",
    "publicationStatus": "draft",
    "owner": "AI Tools",
    "updated": "2026-05-08",
    "checklist": {
      "definition": true,
      "skillDraft": true,
      "references": false,
      "reviewed": false,
      "published": false
    },
    "links": []
  },
  {
    "id": "ucsd-brand-review",
    "name": "ucsd-brand-review",
    "title": "UCSD Brand Review",
    "description": "Check UC San Diego websites, emails, and visual materials against UCSD brand guidance for colors, logos, typography, and tone.",
    "category": "Brand",
    "status": "in-progress",
    "publicationStatus": "draft",
    "owner": "AI Tools",
    "updated": "2026-05-08",
    "checklist": {
      "definition": true,
      "skillDraft": true,
      "references": false,
      "reviewed": false,
      "published": false
    },
    "links": []
  },
  {
    "id": "tritonai-feedback",
    "name": "tritonai-feedback",
    "title": "TritonAI Feedback",
    "description": "Collect feedback, bug reports, support requests, and improvement ideas from coding-agent users, then draft or send them to tritonai@ucsd.edu with confirmation.",
    "category": "Feedback",
    "status": "done",
    "publicationStatus": "draft",
    "owner": "AI Tools",
    "updated": "2026-05-13",
    "checklist": {
      "definition": true,
      "skillDraft": true,
      "references": false,
      "reviewed": true,
      "published": false
    },
    "links": [
      {
        "label": "Skill",
        "url": "skills/tritonai-feedback/SKILL.md"
      }
    ]
  }
]
